cursor_notifier.py
cursor_notifier-0.1.2.dist-info/licenses/LICENSE
cursor_notifier-0.1.2.dist-info/METADATA
cursor_notifier-0.1.2.dist-info/WHEEL
cursor_notifier-0.1.2.dist-info/entry_points.txt
cursor_notifier-0.1.2.dist-info/top_level.txt
cursor_notifier-0.1.2.dist-info/RECORD
