Metadata-Version: 2.4
Name: cursor-notifier
Version: 0.1.2
Summary: Discord webhook notifier for cursor-agent activity in tmux panes
Author-email: Daniel Bowen <dnielbowen@gmail.com>
License: MIT
Project-URL: Homepage, https://github.com/dnielbowen/cursor-notifier
Project-URL: Issues, https://github.com/dnielbowen/cursor-notifier/issues
Keywords: tmux,discord,webhook,cursor-agent,notifier
Classifier: Programming Language :: Python :: 3
Classifier: License :: OSI Approved :: MIT License
Classifier: Operating System :: POSIX :: Linux
Requires-Python: >=3.8
License-File: LICENSE
Requires-Dist: python-dotenv>=1.0
Dynamic: license-file
